GICTrack.py
gictrack/Centenary_Institute_logo.png
gictrack/GIC.png
gictrack/__init__.py
gictrack/SPT_LocAndTrack/LICENSE.md
gictrack/SPT_LocAndTrack/MemoryEfficientND2reader.m
gictrack/SPT_LocAndTrack/MemoryEfficientND2reader_2colors.m
gictrack/SPT_LocAndTrack/ParallelProcess_fastSPT_JF549.m
gictrack/SPT_LocAndTrack/ParallelProcess_fastSPT_JF646.m
gictrack/SPT_LocAndTrack/ParallelProcess_slowSPT_JF646.m
gictrack/SPT_LocAndTrack/README.md
gictrack/SPT_LocAndTrack/SerialProcess_PALM_2color_549_646_ND2_v3.m
gictrack/SPT_LocAndTrack/SerialProcess_PALM_JF549.m
gictrack/SPT_LocAndTrack/SerialProcess_PALM_JF646.m
gictrack/SPT_LocAndTrack/SerialProcess_fastSPT_2color_549_646.m
gictrack/SPT_LocAndTrack/SerialProcess_fastSPT_JF549.m
gictrack/SPT_LocAndTrack/SerialProcess_fastSPT_JF549_TIFF.m
gictrack/SPT_LocAndTrack/SerialProcess_fastSPT_JF646.m
gictrack/SPT_LocAndTrack/UploadExistingData.m
gictrack/SPT_LocAndTrack/__init__.py
gictrack/SPT_LocAndTrack/computeMSD.m
gictrack/SPT_LocAndTrack/fastSPT_3D.m
gictrack/SPT_LocAndTrack/fastSPT_JF549_TIFF_Diffusion.m
gictrack/SPT_LocAndTrack/fastSPT_JF549_TIFF_Diffusion_Local.m
gictrack/SPT_LocAndTrack/fastSPT_JF549_TIFF_Diffusion_v221124.m
gictrack/SPT_LocAndTrack/fastSPT_JF549_TIFF_Diffusion_v230301.m
gictrack/SPT_LocAndTrack/fastSPT_JF549_TIFF_Diffusion_v230309_PreCleanUp.m
gictrack/SPT_LocAndTrack/get_autocorr.m
gictrack/SPT_LocAndTrack/tiffread.m
gictrack/SPT_LocAndTrack/Batch_MTT_code/ReadImageJROI.m
gictrack/SPT_LocAndTrack/Batch_MTT_code/all_max_2d.m
gictrack/SPT_LocAndTrack/Batch_MTT_code/bfmatlab.zip
gictrack/SPT_LocAndTrack/Batch_MTT_code/buildTracks2.m
gictrack/SPT_LocAndTrack/Batch_MTT_code/buildTracks2_ASH.m
gictrack/SPT_LocAndTrack/Batch_MTT_code/carte_H0H1_1vue.m
gictrack/SPT_LocAndTrack/Batch_MTT_code/deflat_part_est.m
gictrack/SPT_LocAndTrack/Batch_MTT_code/deplt_GN_estimation.m
gictrack/SPT_LocAndTrack/Batch_MTT_code/detect_et_estime_part_1vue.m
GICTrack-0.0.12.dist-info/LICENSE
GICTrack-0.0.12.dist-info/METADATA
GICTrack-0.0.12.dist-info/WHEEL
GICTrack-0.0.12.dist-info/top_level.txt
GICTrack-0.0.12.dist-info/RECORD
