Metadata-Version: 2.1
Name: GICTrack
Version: 0.0.12
Author-email: Yeuyo <yewyanwong@gmail.com>
Project-URL: Homepage, https://github.com/GenomeImagingCentre/GIC-Track
Project-URL: Issues, https://github.com/GenomeImagingCentre/GIC-Track/issues
Classifier: Programming Language :: Python :: 3.11
Classifier: License :: OSI Approved :: MIT License
Classifier: Operating System :: OS Independent
Requires-Python: >=3.10
License-File: LICENSE
Requires-Dist: PyQt6==6.4.2
Requires-Dist: PyQt6-Qt6==6.4.3
Requires-Dist: PyQt6-WebEngine==6.4.0
Requires-Dist: PyQt6-WebEngine-Qt6==6.4.3
Requires-Dist: plotly
Requires-Dist: numpy
Requires-Dist: dfply
Requires-Dist: scipy
Requires-Dist: matplotlib
Requires-Dist: pointpats
Requires-Dist: stats
Requires-Dist: h5py
Requires-Dist: pandas==2.1.3
Requires-Dist: kaleido
